[{"feature_name": "macro usage", "feature_type": "macro", "categories": [{"category": "cryptocurrencies", "percent": 20.739703117426807}, {"category": "database", "percent": 21.179692555875484}, {"category": "gaming", "percent": 9.177056217746724}, {"category": "image_processing", "percent": 22.857600512574084}, {"category": "security_tools", "percent": 21.565509320611362}, {"category": "system_tool", "percent": 25.177414378278307}, {"category": "web", "percent": 14.902818807944765}, {"category": "os", "percent": 11.711275064175059}]}, {"feature_name": "tuple struct pattern", "feature_type": "pattern", "categories": [{"category": "cryptocurrencies", "percent": 8.749886818179398}, {"category": "database", "percent": 10.650809877979011}, {"category": "gaming", "percent": 14.488286066584463}, {"category": "image_processing", "percent": 15.313150728816275}, {"category": "security_tools", "percent": 12.103542715787615}, {"category": "system_tool", "percent": 12.8869690424766}, {"category": "web", "percent": 13.086896927490827}, {"category": "os", "percent": 9.478162528946093}]}, {"feature_name": "trait reference", "feature_type": "polymorphism", "categories": [{"category": "cryptocurrencies", "percent": 12.283290102316366}, {"category": "database", "percent": 8.104407199332215}, {"category": "gaming", "percent": 8.907612915011189}, {"category": "image_processing", "percent": 3.908377382668589}, {"category": "security_tools", "percent": 7.058927467090732}, {"category": "system_tool", "percent": 4.679625629949604}, {"category": "web", "percent": 10.126765479605996}, {"category": "os", "percent": 9.72947744448633}]}, {"feature_name": "closure", "feature_type": "polymorphism", "categories": [{"category": "cryptocurrencies", "percent": 7.283050423166854}, {"category": "database", "percent": 6.064471351797488}, {"category": "gaming", "percent": 11.165913138786134}, {"category": "image_processing", "percent": 5.510171391958994}, {"category": "security_tools", "percent": 5.530523897870836}, {"category": "system_tool", "percent": 4.340224210634578}, {"category": "web", "percent": 5.498846425622121}, {"category": "os", "percent": 5.584576444611987}]}, {"feature_name": "generics", "feature_type": "polymorphism", "categories": [{"category": "cryptocurrencies", "percent": 6.979989454117422}, {"category": "database", "percent": 4.712955233959539}, {"category": "gaming", "percent": 4.733525140430197}, {"category": "image_processing", "percent": 2.1944577927278552}, {"category": "security_tools", "percent": 2.385369732308508}, {"category": "system_tool", "percent": 3.0340429908464466}, {"category": "web", "percent": 7.2151607767684585}, {"category": "os", "percent": 6.090796488771608}]}, {"feature_name": "try", "feature_type": "exception", "categories": [{"category": "cryptocurrencies", "percent": 7.148297479107968}, {"category": "database", "percent": 7.116796878663678}, {"category": "gaming", "percent": 3.1351326665753296}, {"category": "image_processing", "percent": 5.253884350472529}, {"category": "security_tools", "percent": 15.761109638660658}, {"category": "system_tool", "percent": 11.724776303609998}, {"category": "web", "percent": 3.8523424796315373}, {"category": "os", "percent": 4.202344409140682}]}, {"feature_name": "lifetime", "feature_type": "safety", "categories": [{"category": "cryptocurrencies", "percent": 3.647384035238161}, {"category": "database", "percent": 3.9560686919087233}, {"category": "gaming", "percent": 6.153811024341234}, {"category": "image_processing", "percent": 3.1715521383950023}, {"category": "security_tools", "percent": 1.6962629207527165}, {"category": "system_tool", "percent": 4.288799753162604}, {"category": "web", "percent": 7.358186972697321}, {"category": "os", "percent": 15.191986644407345}]}, {"feature_name": "wildcard pattern", "feature_type": "pattern", "categories": [{"category": "cryptocurrencies", "percent": 4.7967787122305605}, {"category": "database", "percent": 5.131259320396545}, {"category": "gaming", "percent": 9.88491574188245}, {"category": "image_processing", "percent": 5.814512253724171}, {"category": "security_tools", "percent": 3.6575669228730456}, {"category": "system_tool", "percent": 3.805409852926052}, {"category": "web", "percent": 5.2442938507249215}, {"category": "os", "percent": 5.372753872942359}]}, {"feature_name": "Result", "feature_type": "exception", "categories": [{"category": "cryptocurrencies", "percent": 5.025272834765195}, {"category": "database", "percent": 5.827182262406093}, {"category": "gaming", "percent": 1.6257934876923779}, {"category": "image_processing", "percent": 2.4987986544930325}, {"category": "security_tools", "percent": 10.477957416732927}, {"category": "system_tool", "percent": 6.60290033940142}, {"category": "web", "percent": 3.4079396565668607}, {"category": "os", "percent": 5.554059633439245}]}, {"feature_name": "tuple pattern", "feature_type": "pattern", "categories": [{"category": "cryptocurrencies", "percent": 4.180536987818973}, {"category": "database", "percent": 4.9155419664043665}, {"category": "gaming", "percent": 9.622322692606293}, {"category": "image_processing", "percent": 5.654332852795131}, {"category": "security_tools", "percent": 2.862443678770209}, {"category": "system_tool", "percent": 3.661421372004525}, {"category": "web", "percent": 3.2104272907603377}, {"category": "os", "percent": 3.0085985603245553}]}, {"feature_name": "match", "feature_type": "pattern", "categories": [{"category": "cryptocurrencies", "percent": 3.291593653296121}, {"category": "database", "percent": 4.278706821357893}, {"category": "gaming", "percent": 5.098871991597022}, {"category": "image_processing", "percent": 6.551337497997757}, {"category": "security_tools", "percent": 3.3130135170951496}, {"category": "system_tool", "percent": 5.903527717782577}, {"category": "web", "percent": 5.519278739326245}, {"category": "os", "percent": 5.308130037517727}]}, {"feature_name": "if let", "feature_type": "handy", "categories": [{"category": "cryptocurrencies", "percent": 1.7400706254560563}, {"category": "database", "percent": 2.5004455032310706}, {"category": "gaming", "percent": 3.9914143489975795}, {"category": "image_processing", "percent": 6.054781355117732}, {"category": "security_tools", "percent": 3.4190299496421948}, {"category": "system_tool", "percent": 5.399568034557236}, {"category": "web", "percent": 3.4062369637581837}, {"category": "os", "percent": 2.0679627335882382}]}, {"feature_name": "where constraint", "feature_type": "polymorphism", "categories": [{"category": "cryptocurrencies", "percent": 2.009576513573829}, {"category": "database", "percent": 1.4931392502415097}, {"category": "gaming", "percent": 0.703292688496141}, {"category": "image_processing", "percent": 0.11212558065032836}, {"category": "security_tools", "percent": 0.4329004329004329}, {"category": "system_tool", "percent": 0.5656690321917104}, {"category": "web", "percent": 2.541269016950307}, {"category": "os", "percent": 0.7413790008437001}]}, {"feature_name": "await", "feature_type": "async", "categories": [{"category": "cryptocurrencies", "percent": 1.8114417499773636}, {"category": "database", "percent": 2.5464026786467957}, {"category": "gaming", "percent": 0.8517148467826643}, {"category": "security_tools", "percent": 1.5990811909179257}, {"category": "system_tool", "percent": 0.051424457471973675}, {"category": "web", "percent": 1.3076680770638764}, {"category": "os", "percent": 0.037697237331035596}]}, {"feature_name": "Arc", "feature_type": "pointer", "categories": [{"category": "cryptocurrencies", "percent": 1.502521957273197}, {"category": "database", "percent": 1.412479717879217}, {"category": "gaming", "percent": 0.9681691555920903}, {"category": "image_processing", "percent": 0.8970046452026269}, {"category": "security_tools", "percent": 4.028624436787702}, {"category": "system_tool", "percent": 1.2239020878329734}, {"category": "web", "percent": 1.1263312929397842}, {"category": "os", "percent": 0.6570089934837633}]}]
