[{"percent": 17.8020084698089, "name": "macro usage", "f_type": "macro", "count": 95885}, {"percent": 10.83511721643685, "name": "tuple struct pattern", "f_type": "pattern", "count": 58360}, {"percent": 10.10305986235168, "name": "trait reference", "f_type": "polymorphism", "count": 54417}, {"percent": 6.6822744834474825, "name": "closure", "f_type": "polymorphism", "count": 35992}, {"percent": 6.084634964603922, "name": "generics", "f_type": "polymorphism", "count": 32773}, {"percent": 6.0339497863981775, "name": "try", "f_type": "exception", "count": 32500}, {"percent": 5.88059463182695, "name": "lifetime", "f_type": "safety", "count": 31674}, {"percent": 5.40381976870478, "name": "wildcard pattern", "f_type": "pattern", "count": 29106}, {"percent": 4.723375892792493, "name": "Result", "f_type": "exception", "count": 25441}, {"percent": 4.4157372836829, "name": "tuple pattern", "f_type": "pattern", "count": 23784}, {"percent": 4.413695023755196, "name": "match", "f_type": "pattern", "count": 23773}, {"percent": 2.622261747171934, "name": "if let", "f_type": "handy", "count": 14124}, {"percent": 1.7047300596525559, "name": "where constraint", "f_type": "polymorphism", "count": 9182}, {"percent": 1.5283530658963014, "name": "await", "f_type": "async", "count": 8232}, {"percent": 1.3128018135268158, "name": "Arc", "f_type": "pointer", "count": 7071}]
