[{"name": "slice pattern", "count": 1, "f_type": "pattern", "percent": 0.0014102184428367954}, {"name": "async", "count": 2, "f_type": "async", "percent": 0.002820436885673591}, {"name": "type never", "count": 2, "f_type": "handy", "percent": 0.002820436885673591}, {"name": "await", "count": 3, "f_type": "async", "percent": 0.004230655328510386}, {"name": "const fn", "count": 10, "f_type": "handy", "percent": 0.014102184428367956}, {"name": "trait multi inherited", "count": 32, "f_type": "polymorphism", "percent": 0.04512699017077745}, {"name": "trait single inherited", "count": 37, "f_type": "polymorphism", "percent": 0.05217808238496143}, {"name": "range pattern", "count": 49, "f_type": "pattern", "percent": 0.06910070369900298}, {"name": "operator overload", "count": 75, "f_type": "handy", "percent": 0.10576638321275966}, {"name": "bare fn", "count": 80, "f_type": "polymorphism", "percent": 0.11281747542694365}]
